syntaxility_pypi_response_manager/__init__.py
syntaxility_pypi_response_manager/decorators.py
syntaxility_pypi_response_manager/manager.py
syntaxility_pypi_response_manager/ml_types.py
syntaxility_pypi_response_manager/pagination.py
syntaxility_pypi_response_manager/types.py
syntaxility_pypi_response_manager-1.0.0.dist-info/licenses/LICENSE
syntaxility_pypi_response_manager-1.0.0.dist-info/METADATA
syntaxility_pypi_response_manager-1.0.0.dist-info/WHEEL
syntaxility_pypi_response_manager-1.0.0.dist-info/top_level.txt
syntaxility_pypi_response_manager-1.0.0.dist-info/RECORD
