Metadata-Version: 2.4
Name: syntaxility-pypi-response-manager
Version: 1.0.0
Summary: SyntaxilitY PyPi Response Manager for FAST APIs, REST APIs, Machine Learning, Deep Learning and AI responses
Author-email: Tariq Mehmood <info.syntaxility@gmail.com>
License: MIT
Project-URL: Homepage, https://github.com/SyntaxilitY/SyntaxilitY-PyPi-Response-Manager-Decorators.git
Requires-Python: >=3.9
License-File: LICENSE
Requires-Dist: annotated-doc==0.0.4
Requires-Dist: annotated-types==0.7.0
Requires-Dist: anyio==4.12.1
Requires-Dist: certifi==2026.1.4
Requires-Dist: click==8.3.1
Requires-Dist: colorama==0.4.6
Requires-Dist: fastapi==0.128.0
Requires-Dist: h11==0.16.0
Requires-Dist: httpcore==1.0.9
Requires-Dist: httpx==0.28.1
Requires-Dist: idna==3.11
Requires-Dist: iniconfig==2.3.0
Requires-Dist: packaging==25.0
Requires-Dist: pluggy==1.6.0
Requires-Dist: pydantic==2.12.5
Requires-Dist: pydantic_core==2.41.5
Requires-Dist: Pygments==2.19.2
Requires-Dist: pytest==9.0.2
Requires-Dist: starlette==0.50.0
Requires-Dist: typing-inspection==0.4.2
Requires-Dist: typing_extensions==4.15.0
Requires-Dist: uvicorn==0.40.0
Dynamic: license-file
